Metadata-Version: 2.2
Name: mc-data-files
Version: 3.83.1rc0
Summary: Minecraft Data tracking PrismarineJS/minecraft-data
Author-email: hunter <huntcsg@gmail.com>
License: MIT License
Project-URL: Homepage, https://github.com/mc-bench/mc-data-files
Project-URL: Repository, https://github.com/mc-bench/mc-data-files.git
Project-URL: Issues, https://github.com/mc-bench/mc-data-files/issues
Requires-Python: <3.14,>=3.9
License-File: LICENSE
Provides-Extra: dev
Requires-Dist: ruff>=0.3.0; extra == "dev"
Requires-Dist: mypy>=1.8.0; extra == "dev"
Requires-Dist: pytest>=8.0.0; extra == "dev"
Requires-Dist: pytest-cov>=4.1.0; extra == "dev"
Requires-Dist: build>=1.0.0; extra == "dev"
